mdium/__init__.py
mdium/cli.py
mdium/mdium.py
mdium-2.0.0.dist-info/METADATA
mdium-2.0.0.dist-info/WHEEL
mdium-2.0.0.dist-info/entry_points.txt
mdium-2.0.0.dist-info/top_level.txt
mdium-2.0.0.dist-info/RECORD
