Metadata-Version: 2.1
Name: mdium
Version: 2.0.0
Summary: Publish your markdown to Medium, from the CLI
Home-page: https://github.com/icyphox/mdium
Author: Anirudh
Author-email: icyph0x@pm.me
License: MIT
Platform: UNKNOWN
Requires-Dist: python-frontmatter
Requires-Dist: requests
